unionfind_link/UnionFind.py
unionfind_link/__init__.py
unionfind_link-1.0.0.dist-info/LICENSE
unionfind_link-1.0.0.dist-info/METADATA
unionfind_link-1.0.0.dist-info/WHEEL
unionfind_link-1.0.0.dist-info/top_level.txt
unionfind_link-1.0.0.dist-info/RECORD
