Metadata-Version: 2.2
Name: unionfind_link
Version: 1.0.0
Summary: simple UnionFind model with test on element is inside. How to use, see jupyter book in https://github.com/BastiYourDeveloper/clustering-closest-pairs 
Home-page: https://github.com/BastiYourDeveloper/unionfind-link.git
Author: Basti.YourDeveloper
Author-email: basti.yourDeveloper@gmail.com
License: LGPL-3.0
Classifier: Programming Language :: Python :: 3
Classifier: Operating System :: OS Independent
License-File: LICENSE
Dynamic: author
Dynamic: author-email
Dynamic: classifier
Dynamic: description
Dynamic: description-content-type
Dynamic: home-page
Dynamic: license
Dynamic: summary
